pymanhuagui/__init__.py
pymanhuagui/__main__.py
pymanhuagui/cli.py
pymanhuagui/exceptions.py
pymanhuagui/manhuagui.py
pymanhuagui-3.0.0.dist-info/METADATA
pymanhuagui-3.0.0.dist-info/WHEEL
pymanhuagui-3.0.0.dist-info/entry_points.txt
pymanhuagui-3.0.0.dist-info/RECORD
