Metadata-Version: 2.3
Name: pymanhuagui
Version: 3.0.0
Summary: Manga Downloader for www.manhuagui.com
Project-URL: Homepage, https://github.com/tabris17/pymanhuagui
Project-URL: Bug Tracker, https://github.com/tabris17/pymanhuagui/issues
Author-email: fournoas <admin@fournoas.com>
License: MIT License
Requires-Python: >=3.8
Requires-Dist: beautifulsoup4>=4.12.3
Requires-Dist: lxml>=5.2.2
Requires-Dist: lzstring>=1.0.4
Requires-Dist: requests>=2.32.3
